[
  {
    "id": "GR7vTA_btqTnLtXcEDX8C",
    "companyId": "pVbRRBQtMVw6lUAkj1k43",
    "title": "Backend Developer",
    "description": "We are looking for a Backend Developer familiar with Node.js and Express."
  },
  {
    "id": "yX71WsWqBRAFuMAIDj4W0",
    "companyId": "wvdB54Gqbdp_NZTXK9Tue",
    "title": "Full-Stack Developer",
    "description": "We are looking for a Full-Stack Developer familiar with Node.js, Express, and React."
  },
  {
    "id": "NKINYJqE1srHVtliiHTVz",
    "title": "dasdsa",
    "companyId": "pVbRRBQtMVw6lUAkj1k43",
    "description": "sadsaddas"
  },
  {
    "id": "mzguJjef4PFSYHNTWfEV9",
    "title": "dsaasd",
    "companyId": "pVbRRBQtMVw6lUAkj1k43",
    "description": "dsasad"
  },
  {
    "id": "hbgf7S6uXDr2gFuBVkteF",
    "title": "Job 3",
    "description": "test desc 3",
    "companyId": "wvdB54Gqbdp_NZTXK9Tue"
  }
]